setup.cfg
setup.py
modules/TenvisAudio.py
modules/TenvisMotor.py
modules/TenvisVideo.py
modules/__init__.py
pyTenvis.egg-info/PKG-INFO
pyTenvis.egg-info/SOURCES.txt
pyTenvis.egg-info/dependency_links.txt
pyTenvis.egg-info/top_level.txt