Metadata-Version: 1.1
Name: pyTenvis
Version: 0.11
Summary: Library for Tenvis HD IPCAMs
Home-page: https://github.com/SimBil91/pyTenvis
Author: Simon Bilgeri
Author-email: Simon.Bilgeri@tum.de
License: UNKNOWN
Download-URL: https://github.com/SimBil91/pyTenvis/tarball/0.11
Keywords: TENVIS,IPCAM,library
Platform: UNKNOWN
